AUTHORS.md
LICENSE
MANIFEST.in
README.md
pyproject.toml
requirements-dev.txt
requirements.txt
setup.cfg
setup.py
moto/__init__.py
moto/backend_index.py
moto/backends.py
moto/server.py
moto/settings.py
moto/acm/__init__.py
moto/acm/exceptions.py
moto/acm/models.py
moto/acm/responses.py
moto/acm/urls.py
moto/acm/utils.py
moto/acmpca/__init__.py
moto/acmpca/exceptions.py
moto/acmpca/models.py
moto/acmpca/responses.py
moto/acmpca/urls.py
moto/amp/__init__.py
moto/amp/exceptions.py
moto/amp/models.py
moto/amp/responses.py
moto/amp/urls.py
moto/amp/utils.py
moto/apigateway/__init__.py
moto/apigateway/exceptions.py
moto/apigateway/models.py
moto/apigateway/responses.py
moto/apigateway/urls.py
moto/apigateway/utils.py
moto/apigateway/integration_parsers/__init__.py
moto/apigateway/integration_parsers/aws_parser.py
moto/apigateway/integration_parsers/http_parser.py
moto/apigateway/integration_parsers/unknown_parser.py
moto/apigatewayv2/__init__.py
moto/apigatewayv2/exceptions.py
moto/apigatewayv2/models.py
moto/apigatewayv2/responses.py
moto/apigatewayv2/urls.py
moto/applicationautoscaling/__init__.py
moto/applicationautoscaling/exceptions.py
moto/applicationautoscaling/models.py
moto/applicationautoscaling/responses.py
moto/applicationautoscaling/urls.py
moto/applicationautoscaling/utils.py
moto/appsync/__init__.py
moto/appsync/exceptions.py
moto/appsync/models.py
moto/appsync/responses.py
moto/appsync/urls.py
moto/athena/__init__.py
moto/athena/exceptions.py
moto/athena/models.py
moto/athena/responses.py
moto/athena/urls.py
moto/athena/utils.py
moto/autoscaling/__init__.py
moto/autoscaling/exceptions.py
moto/autoscaling/models.py
moto/autoscaling/responses.py
moto/autoscaling/urls.py
moto/awslambda/__init__.py
moto/awslambda/exceptions.py
moto/awslambda/models.py
moto/awslambda/policy.py
moto/awslambda/responses.py
moto/awslambda/urls.py
moto/awslambda/utils.py
moto/batch/__init__.py
moto/batch/exceptions.py
moto/batch/models.py
moto/batch/responses.py
moto/batch/urls.py
moto_improved_cognitoidentity.egg-info/PKG-INFO
moto_improved_cognitoidentity.egg-info/SOURCES.txt
moto_improved_cognitoidentity.egg-info/dependency_links.txt
moto_improved_cognitoidentity.egg-info/entry_points.txt
moto_improved_cognitoidentity.egg-info/requires.txt
moto_improved_cognitoidentity.egg-info/top_level.txt
