Metadata-Version: 2.1
Name: moto-improved-cognitoidentity
Version: 1.3
Summary: UNKNOWN
Home-page: https://github.com/emusiyenko/moto-cognitoidentity-improved
Author: Steve Pulec, Eugene Musiienko
Author-email: spulec@gmail.com, evgeniy.musiyenko@icloud.com
License: Apache License 2.0
Project-URL: Documentation, http://docs.getmoto.org/en/latest/
Project-URL: Issue tracker, https://github.com/getmoto/moto/issues
Project-URL: Changelog, https://github.com/getmoto/moto/blob/master/CHANGELOG.md
Keywords: aws ec2 s3 boto3 mock moto cognitoidentity get_id
Platform: UNKNOWN
Classifier: Programming Language :: Python :: 3
Classifier: Programming Language :: Python :: 3.7
Classifier: Programming Language :: Python :: 3.8
Classifier: Programming Language :: Python :: 3.9
Classifier: Programming Language :: Python :: 3.10
Classifier: Programming Language :: Python :: 3.11
Classifier: License :: OSI Approved :: Apache Software License
Classifier: Topic :: Software Development :: Testing
Requires-Python: >=3.7
Provides-Extra: all
Provides-Extra: server
Provides-Extra: acm
Provides-Extra: acmpca
Provides-Extra: amp
Provides-Extra: apigateway
Provides-Extra: apigatewayv2
Provides-Extra: applicationautoscaling
Provides-Extra: appsync
Provides-Extra: athena
Provides-Extra: autoscaling
Provides-Extra: awslambda
Provides-Extra: batch
Provides-Extra: batch_simple
Provides-Extra: budgets
Provides-Extra: ce
Provides-Extra: cloudformation
Provides-Extra: cloudfront
Provides-Extra: cloudtrail
Provides-Extra: cloudwatch
Provides-Extra: codebuild
Provides-Extra: codecommit
Provides-Extra: codepipeline
Provides-Extra: cognitoidentity
Provides-Extra: cognitoidp
Provides-Extra: comprehend
Provides-Extra: config
Provides-Extra: databrew
Provides-Extra: datapipeline
Provides-Extra: datasync
Provides-Extra: dax
Provides-Extra: dms
Provides-Extra: ds
Provides-Extra: dynamodb
Provides-Extra: dynamodbstreams
Provides-Extra: ebs
Provides-Extra: ec2
Provides-Extra: ec2instanceconnect
Provides-Extra: ecr
Provides-Extra: ecs
Provides-Extra: efs
Provides-Extra: eks
Provides-Extra: elasticache
Provides-Extra: elasticbeanstalk
Provides-Extra: elastictranscoder
Provides-Extra: elb
Provides-Extra: elbv2
Provides-Extra: emr
Provides-Extra: emrcontainers
Provides-Extra: emrserverless
Provides-Extra: es
Provides-Extra: events
Provides-Extra: firehose
Provides-Extra: forecast
Provides-Extra: glacier
Provides-Extra: glue
Provides-Extra: greengrass
Provides-Extra: guardduty
Provides-Extra: iam
Provides-Extra: iot
Provides-Extra: iotdata
Provides-Extra: kinesis
Provides-Extra: kinesisvideo
Provides-Extra: kinesisvideoarchivedmedia
Provides-Extra: kms
Provides-Extra: logs
Provides-Extra: managedblockchain
Provides-Extra: mediaconnect
Provides-Extra: medialive
Provides-Extra: mediapackage
Provides-Extra: mediastore
Provides-Extra: mediastoredata
Provides-Extra: meteringmarketplace
Provides-Extra: mq
Provides-Extra: opsworks
Provides-Extra: organizations
Provides-Extra: personalize
Provides-Extra: pinpoint
Provides-Extra: polly
Provides-Extra: quicksight
Provides-Extra: ram
Provides-Extra: rds
Provides-Extra: redshift
Provides-Extra: redshiftdata
Provides-Extra: rekognition
Provides-Extra: resourcegroups
Provides-Extra: resourcegroupstaggingapi
Provides-Extra: route53
Provides-Extra: route53resolver
Provides-Extra: s3
Provides-Extra: s3control
Provides-Extra: sagemaker
Provides-Extra: sdb
Provides-Extra: secretsmanager
Provides-Extra: servicediscovery
Provides-Extra: servicequotas
Provides-Extra: ses
Provides-Extra: signer
Provides-Extra: sns
Provides-Extra: sqs
Provides-Extra: ssm
Provides-Extra: ssoadmin
Provides-Extra: stepfunctions
Provides-Extra: sts
Provides-Extra: support
Provides-Extra: swf
Provides-Extra: textract
Provides-Extra: timestreamwrite
Provides-Extra: transcribe
Provides-Extra: wafv2
Provides-Extra: xray
